LICENSE.txt
MANIFEST.in
README.rst
requirements.txt
setup.cfg
setup.py
botocorev063p/__init__.py
botocorev063p/auth.py
botocorev063p/awsrequest.py
botocorev063p/compat.py
botocorev063p/config.py
botocorev063p/credentials.py
botocorev063p/endpoint.py
botocorev063p/exceptions.py
botocorev063p/handlers.py
botocorev063p/hooks.py
botocorev063p/loaders.py
botocorev063p/operation.py
botocorev063p/paginate.py
botocorev063p/parameters.py
botocorev063p/payload.py
botocorev063p/provider.py
botocorev063p/regions.py
botocorev063p/response.py
botocorev063p/retryhandler.py
botocorev063p/service.py
botocorev063p/session.py
botocorev063p/translate.py
botocorev063p/utils.py
botocorev063p/waiter.py
botocorev063p.egg-info/PKG-INFO
botocorev063p.egg-info/SOURCES.txt
botocorev063p.egg-info/dependency_links.txt
botocorev063p.egg-info/requires.txt
botocorev063p.egg-info/top_level.txt
botocorev063p/data/aws/_endpoints.json
botocorev063p/data/aws/_retry.json
botocorev063p/data/aws/autoscaling/2011-01-01.json
botocorev063p/data/aws/cloudformation/2010-05-15.json
botocorev063p/data/aws/cloudfront/2012-05-05.json
botocorev063p/data/aws/cloudfront/2013-05-12.json
botocorev063p/data/aws/cloudfront/2013-11-11.json
botocorev063p/data/aws/cloudfront/2014-05-31.json
botocorev063p/data/aws/cloudsearch/2011-02-01.json
botocorev063p/data/aws/cloudsearch/2013-01-01.json
botocorev063p/data/aws/cloudsearchdomain/2013-01-01.json
botocorev063p/data/aws/cloudtrail/2013-11-01.json
botocorev063p/data/aws/cloudwatch/2010-08-01.json
botocorev063p/data/aws/cognito-identity/2014-06-30.json
botocorev063p/data/aws/cognito-sync/2014-06-30.json
botocorev063p/data/aws/datapipeline/2012-10-29.json
botocorev063p/data/aws/directconnect/2012-10-25.json
botocorev063p/data/aws/dynamodb/2011-12-05.json
botocorev063p/data/aws/dynamodb/2012-08-10.json
botocorev063p/data/aws/ec2/2013-02-01.json
botocorev063p/data/aws/ec2/2013-10-15.json
botocorev063p/data/aws/ec2/2014-02-01.json
botocorev063p/data/aws/ec2/2014-05-01.json
botocorev063p/data/aws/ec2/2014-06-15.json
botocorev063p/data/aws/elasticache/2012-11-15.json
botocorev063p/data/aws/elasticache/2013-06-15.json
