Metadata-Version: 1.1
Name: botocorev063p
Version: 0.63.1
Summary: Low-level, data-driven core of boto 3.
Home-page: https://github.com/boto/botocorev063p
Author: Mitch Garnaat
Author-email: garnaat@amazon.com
License: Copyright 2012-2014 Amazon.com, Inc. or its affiliates. All Rights Reserved.
